game/__init__.py
game/adventure_game.py
adventure_game_2d-0.1.0.dist-info/METADATA
adventure_game_2d-0.1.0.dist-info/WHEEL
adventure_game_2d-0.1.0.dist-info/RECORD
