Metadata-Version: 2.3
Name: adventure_game_2D
Version: 0.1.0
Summary: 
Author: Soliton
Requires-Python: >=3.11,<4.0
Classifier: Programming Language :: Python :: 3
Classifier: Programming Language :: Python :: 3.11
Classifier: Programming Language :: Python :: 3.12
Classifier: Programming Language :: Python :: 3.13
Requires-Dist: inquirer (>=3.4.1,<4.0.0)
Requires-Dist: rich (>=14.1.0,<15.0.0)
